fiu/__init__.py
fiu/driver.py
fiu/fiu_types.py
fiu/interfaces.py
bloomy_fiu-1.1.0.dist-info/LICENSE
bloomy_fiu-1.1.0.dist-info/METADATA
bloomy_fiu-1.1.0.dist-info/WHEEL
bloomy_fiu-1.1.0.dist-info/top_level.txt
bloomy_fiu-1.1.0.dist-info/RECORD
