Metadata-Version: 2.1
Name: bloomy-fiu
Version: 1.1.0
Summary: Python driver package to communicate with the Bloomy Fault Insertion Unit over RS-485 Protocol
Author-email: Mikhail Kharitonov <mikhail.kharitonov@bloomy.com>
Maintainer-email: Mikhail Kharitonov <mikhail.kharitonov@bloomy.com>
License: BSD 3-Clause License
Classifier: Programming Language :: Python :: 3
Classifier: Programming Language :: Python :: 3.7
Classifier: Programming Language :: Python :: 3.8
Classifier: Programming Language :: Python :: 3.9
Classifier: Programming Language :: Python :: 3.10
Classifier: License :: OSI Approved :: BSD License
Classifier: Operating System :: OS Independent
License-File: LICENSE
Requires-Dist: pyserial ==3.5
